lifeguard_tinydb/__init__.py
lifeguard_tinydb/repositories.py
lifeguard_tinydb/settings.py
lifeguard_tinydb-1.2.0.dist-info/METADATA
lifeguard_tinydb-1.2.0.dist-info/WHEEL
lifeguard_tinydb-1.2.0.dist-info/top_level.txt
lifeguard_tinydb-1.2.0.dist-info/RECORD
