Metadata-Version: 2.1
Name: lifeguard-tinydb
Version: 1.2.0
Summary: Lifeguard integration with TinyDB
Home-page: https://github.com/LifeguardSystem/lifeguard-tinydb
Author: Diego Rubin
Author-email: contact@diegorubin.dev
License: GPL2
Classifier: Development Status :: 5 - Production/Stable
Classifier: Environment :: Plugins
Classifier: Intended Audience :: Developers
Classifier: Intended Audience :: Information Technology
Classifier: Programming Language :: Python
Classifier: Programming Language :: Python :: 3
Classifier: Topic :: System :: Monitoring
Requires-Dist: lifeguard
Requires-Dist: tinydb
